README
setup.py
python_weewar.egg-info/PKG-INFO
python_weewar.egg-info/SOURCES.txt
python_weewar.egg-info/dependency_links.txt
python_weewar.egg-info/requires.txt
python_weewar.egg-info/top_level.txt
weewar/__init__.py
weewar/api.py
weewar/version.py