Metadata-Version: 1.0
Name: python-weewar
Version: 0.3.1
Summary: Python wrapper for the Weewar XML API
Home-page: http://bitbucket.org/basti/python-weewar/downloads/
Author: Sebastian Rahlf
Author-email: basti AT redtoad DOT de
License: lgpl
Platform: UNKNOWN
Classifier: Development Status :: 3 - Alpha
Classifier: Intended Audience :: Developers
Classifier: License :: OSI Approved :: GNU Library or Lesser General Public License (LGPL)
Classifier: Programming Language :: Python :: 2.5
Classifier: Programming Language :: Python :: 2.6
Classifier: Topic :: Games/Entertainment :: Turn Based Strategy
